HelloModule/__init__.py
HelloModule/hello.py
mdvazeerhello-0.0.6.dist-info/LICENSE
mdvazeerhello-0.0.6.dist-info/METADATA
mdvazeerhello-0.0.6.dist-info/WHEEL
mdvazeerhello-0.0.6.dist-info/top_level.txt
mdvazeerhello-0.0.6.dist-info/RECORD
